copilot_auth/__init__.py
copilot_auth/auth.py
copilot_auth-0.1.2.dist-info/licenses/LICENSE
copilot_auth-0.1.2.dist-info/METADATA
copilot_auth-0.1.2.dist-info/WHEEL
copilot_auth-0.1.2.dist-info/top_level.txt
copilot_auth-0.1.2.dist-info/RECORD
