Metadata-Version: 2.4
Name: copilot_auth
Version: 0.1.2
Summary: Copilot authentication library to get GitHub and Copilot tokens
Home-page: https://github.com/bhachauk/copilot-auth.git
Author: Bhanuchander Udhayakumar
Author-email: bhanuchander210@gmail.com
License: MIT
License-File: LICENSE
Requires-Dist: requests
Dynamic: author
Dynamic: author-email
Dynamic: description
Dynamic: description-content-type
Dynamic: home-page
Dynamic: license
Dynamic: license-file
Dynamic: requires-dist
Dynamic: summary
